nlx_middleware/__init__.py
nlx_middleware/admin.py
nlx_middleware/apps.py
nlx_middleware/compat.py
nlx_middleware/middleware.py
nlx_middleware/models.py
nlx_middleware/nlx.py
nlx_middleware/settings.py
nlx_middleware/migrations/0001_initial.py
nlx_middleware/migrations/__init__.py
nlx_middleware-0.2.0.dist-info/METADATA
nlx_middleware-0.2.0.dist-info/RECORD
nlx_middleware-0.2.0.dist-info/WHEEL
nlx_middleware-0.2.0.dist-info/top_level.txt
testapp/__init__.py
testapp/settings.py
testapp/urls.py
tests/__init__.py
tests/conftest.py
