Metadata-Version: 2.1
Name: nlx-middleware
Version: 0.2.0
Summary: TODO
Home-page: https://github.com/maykinmedia/nlx_middleware
Author: Maykin Media
Author-email: support@maykinmedia.nl
License: MIT
Keywords: TODO
Platform: UNKNOWN
Classifier: Development Status :: 3 - Alpha
Classifier: Framework :: Django
Classifier: Framework :: Django :: 1.11
Classifier: Framework :: Django :: 2.0
Classifier: Framework :: Django :: 2.1
Classifier: Intended Audience :: Developers
Classifier: Operating System :: Unix
Classifier: Operating System :: MacOS
Classifier: Operating System :: Microsoft :: Windows
Classifier: Programming Language :: Python :: 3.6
Classifier: Topic :: Software Development :: Libraries :: Python Modules
Provides-Extra: release
Provides-Extra: docs
Provides-Extra: tests
Provides-Extra: pep8
Provides-Extra: coverage
Requires-Dist: django
Requires-Dist: django-app-settings
Requires-Dist: gemma-zds-client (>=0.4.1)
Provides-Extra: coverage
Requires-Dist: pytest-cov; extra == 'coverage'
Provides-Extra: docs
Requires-Dist: sphinx; extra == 'docs'
Requires-Dist: sphinx-rtd-theme; extra == 'docs'
Provides-Extra: pep8
Requires-Dist: flake8; extra == 'pep8'
Provides-Extra: release
Requires-Dist: zest.releaser; extra == 'release'
Provides-Extra: tests
Requires-Dist: pytest; extra == 'tests'
Requires-Dist: pytest-django; extra == 'tests'
Requires-Dist: tox; extra == 'tests'
Requires-Dist: isort; extra == 'tests'
